printfile/__init__.py
printfile/printfun.py
printfile-0.0.0.dist-info/METADATA
printfile-0.0.0.dist-info/WHEEL
printfile-0.0.0.dist-info/top_level.txt
printfile-0.0.0.dist-info/RECORD
